makepyeasy/__init__.py
makepyeasy-1.0.0.dist-info/METADATA
makepyeasy-1.0.0.dist-info/WHEEL
makepyeasy-1.0.0.dist-info/top_level.txt
makepyeasy-1.0.0.dist-info/RECORD
