Metadata-Version: 2.1
Name: makepyeasy
Version: 1.0.0
Summary: A python library to make code shorter
Home-page: UNKNOWN
Author: Viraj Khanna
Author-email: viraj@virajkhanna.in
License: UNKNOWN
Keywords: makepyeasy,easy python,python easy,make py easy
Platform: UNKNOWN
Classifier: Development Status :: 4 - Beta
Classifier: Intended Audience :: Developers
Classifier: Natural Language :: English
Classifier: Operating System :: OS Independent
Classifier: Programming Language :: Python :: 3
Classifier: Topic :: Software Development
Requires: requests
